Workbook
Name Scenario: Inputs!$C$4
Name WACC: Inputs!$C$7
Name TerminalGrowth: Inputs!$C$8

Sheet Cover
B2: Costco Wholesale: driver-based forecast and DCF
B3: A modelling exercise built from Costco's SEC filings. Not investment advice: there is no buy/sell view here.
B5: How to use
B6: 1. Pick a scenario on Inputs!C4 (1 = Base, 2 = Upside, 3 = Downside). Every sheet recalculates.
B7: 2. Change any yellow cell on Inputs (WACC, terminal growth, long-run growth, scenario deltas).
B8: 3. Checks!C3 must say ALL CHECKS PASS.
B10: Colour key
B11: Blue = typed-in input or source data · Black = formula · Green = link to another sheet
B13: Sheets
B14: Inputs: scenario switch, valuation inputs and the drivers for each scenario
B15: Historicals: FY2021-FY2025 from the SEC's XBRL data, with the ratios the drivers are built on
B16: Forecast: FY2026-FY2030 income-statement items and unlevered free cash flow
... B23: Simplifications: end-of-year discounting, operating leases left out of net debt, interest income left out of EBIT.

Sheet Inputs
B2: Inputs and scenario drivers
B4: Scenario (1 Base, 2 Upside, 3 Downside) | C4: 1 | D4: =CHOOSE(C4,"Base","Upside","Downside")
B6: Valuation
B7: WACC (discount rate) | C7: 0.08
B8: Terminal growth after FY2030 | C8: 0.03
B10: Driver | C10: Base | D10: Upside | E10: Downside | F10: Live | G10: Upside Δ | H10: Downside Δ
B11: FY2026 revenue growth | C11: =Historicals!H27 | D11: =C11+G11 | E11: =C11+H11 | F11: =CHOOSE($C$4,C11,D11,E11) | G11: 0.02 | H11: -0.03
B12: FY2030 revenue growth (fades in a straight line) | C12: 0.04 | D12: =C12+G12 | E12: =C12+H12 | F12: =CHOOSE($C$4,C12,D12,E12) | G12: 0.01 | H12: -0.015
B13: Gross margin | C13: =Historicals!H28 | D13: =C13+G13 | E13: =C13+H13 | F13: =CHOOSE($C$4,C13,D13,E13) | G13: 0.002 | H13: -0.003
B14: SG&A % of revenue | C14: =Historicals!H29 | D14: =C14+G14 | E14: =C14+H14 | F14: =CHOOSE($C$4,C14,D14,E14) | G14: -0.001 | H14: 0.002
B15: D&A % of revenue | C15: =Historicals!H32 | D15: =C15+G15 | E15: =C15+H15 | F15: =CHOOSE($C$4,C15,D15,E15) | G15: 0 | H15: 0
B16: Capex % of revenue | C16: =Historicals!H33 | D16: =C16+G16 | E16: =C16+H16 | F16: =CHOOSE($C$4,C16,D16,E16) | G16: 0 | H16: 0
B17: Net working capital % of revenue | C17: =Historicals!H35 | D17: =C17+G17 | E17: =C17+H17 | F17: =CHOOSE($C$4,C17,D17,E17) | G17: 0 | H17: 0
B18: Tax rate on operating income | C18: =Historicals!H31 | D18: =C18+G18 | E18: =C18+H18 | F18: =CHOOSE($C$4,C18,D18,E18) | G18: 0 | H18: 0
B20: Base margins and ratios are the FY2023-25 averages on Historicals; growth starts at the FY2022-25 CAGR.

Sheet Historicals
B2: Historicals ($ millions, fiscal years)
C3: FY2021 | D3: FY2022 | E3: FY2023 | F3: FY2024 | G3: FY2025 | H3: 3-yr avg
B4: Revenue | C4: 195929 | D4: 226954 | E4: 242290 | F4: 254453 | G4: 275235
B5: Cost of goods sold | C5: 170684 | D5: 199382 | E5: 212586 | F5: 222358 | G5: 239886
B6: Gross profit | C6: =C4-C5 | D6: =D4-D5 | E6: =E4-E5 | F6: =F4-F5 | G6: =G4-G5
B7: SG&A | C7: 18537 | D7: 19779 | E7: 21590 | F7: 22810 | G7: 24966
B8: Operating income (calculated) | C8: =C6-C7 | D8: =D6-D7 | E8: =E6-E7 | F8: =F6-F7 | G8: =G6-G7
B9: Operating income (reported) | C9: 6708 | D9: 7793 | E9: 8114 | F9: 9285 | G9: 10383
B10: Pretax income | C10: 6680 | D10: 7840 | E10: 8487 | F10: 9740 | G10: 10818
B11: Income tax | C11: 1601 | D11: 1925 | E11: 2195 | F11: 2373 | G11: 2719
B12: Net income | C12: 5007 | D12: 5844 | E12: 6292 | F12: 7367 | G12: 8099
B13: D&A | C13: 1781 | D13: 1900 | E13: 2077 | F13: 2237 | G13: 2426
B14: Capex | C14: 3588 | D14: 3891 | E14: 4323 | F14: 4710 | G14: 5498
B15: Operating cash flow | C15: 8958 | D15: 7392 | E15: 11068 | F15: 11339 | G15: 13335
B16: Diluted shares (millions) | C16: 444.346 | D16: 444.757 | E16: 444.452 | F16: 444.759 | G16: 444.803
B17: Balance sheet at year end
B18: Cash and equivalents | C18: 11258 | D18: 10203 | E18: 13700 | F18: 9906 | G18: 14161
B19: Short-term investments | C19: 917 | D19: 846 | E19: 1534 | F19: 1238 | G19: 1123
B20: Debt, current | C20: 799 | D20: 73 | E20: 1081 | F20: 103 | G20: 75
B21: Debt, non-current | C21: 6692 | D21: 6484 | E21: 5377 | F21: 5794 | G21: 5713
B22: Inventory | C22: 14215 | D22: 17907 | E22: 16651 | F22: 18647 | G22: 18116
B23: Receivables | C23: 1803 | D23: 2241 | E23: 2285 | F23: 2721 | G23: 3203
B24: Accounts payable | C24: 16278 | D24: 17848 | E24: 17483 | F24: 19421 | G24: 19783
B26: Ratios
B27: Revenue growth | D27: =D4/C4-1 | E27: =E4/D4-1 | F27: =F4/E4-1 | G27: =G4/F4-1 | H27: =(G4/D4)^(1/3)-1 | I27: CAGR FY2022-25
B28: Gross margin | C28: =C6/C4 | D28: =D6/D4 | E28: =E6/E4 | F28: =F6/F4 | G28: =G6/G4 | H28: =AVERAGE(E28:G28)
B29: SG&A % of revenue | C29: =C7/C4 | D29: =D7/D4 | E29: =E7/E4 | F29: =F7/F4 | G29: =G7/G4 | H29: =AVERAGE(E29:G29)
B30: Operating margin | C30: =C8/C4 | D30: =D8/D4 | E30: =E8/E4 | F30: =F8/F4 | G30: =G8/G4 | H30: =AVERAGE(E30:G30)
B31: Tax rate (tax / pretax income) | C31: =C11/C10 | D31: =D11/D10 | E31: =E11/E10 | F31: =F11/F10 | G31: =G11/G10 | H31: =AVERAGE(E31:G31)
B32: D&A % of revenue | C32: =C13/C4 | D32: =D13/D4 | E32: =E13/E4 | F32: =F13/F4 | G32: =G13/G4 | H32: =AVERAGE(E32:G32)
B33: Capex % of revenue | C33: =C14/C4 | D33: =D14/D4 | E33: =E14/E4 | F33: =F14/F4 | G33: =G14/G4 | H33: =AVERAGE(E33:G33)
B34: Net working capital (inv + rec - pay) | C34: =C22+C23-C24 | D34: =D22+D23-D24 | E34: =E22+E23-E24 | F34: =F22+F23-F24 | G34: =G22+G23-G24
B35: NWC % of revenue | C35: =C34/C4 | D35: =D34/D4 | E35: =E34/E4 | F35: =F34/F4 | G35: =G34/G4 | H35: =AVERAGE(E35:G35)

Sheet Forecast
B2: Forecast ($ millions) | H2: =Inputs!D4
C3: FY2025A | D3: FY2026 | E3: FY2027 | F3: FY2028 | G3: FY2029 | H3: FY2030
B4: Year | C4: 0 | D4: 1 | E4: 2 | F4: 3 | G4: 4 | H4: 5
B5: Revenue growth | D5: =Inputs!$F$11+(Inputs!$F$12-Inputs!$F$11)*(D4-1)/4 | E5: =Inputs!$F$11+(Inputs!$F$12-Inputs!$F$11)*(E4-1)/4 | F5: =Inputs!$F$11+(Inputs!$F$12-Inputs!$F$11)*(F4-1)/4 | G5: =Inputs!$F$11+(Inputs!$F$12-Inputs!$F$11)*(G4-1)/4 | H5: =Inputs!$F$11+(Inputs!$F$12-Inputs!$F$11)*(H4-1)/4
B6: Revenue | C6: =Historicals!G4 | D6: =C6*(1+D5) | E6: =D6*(1+E5) | F6: =E6*(1+F5) | G6: =F6*(1+G5) | H6: =G6*(1+H5)
B7: Gross profit | D7: =D6*Inputs!$F$13 | E7: =E6*Inputs!$F$13 | F7: =F6*Inputs!$F$13 | G7: =G6*Inputs!$F$13 | H7: =H6*Inputs!$F$13
B8: SG&A | D8: =D6*Inputs!$F$14 | E8: =E6*Inputs!$F$14 | F8: =F6*Inputs!$F$14 | G8: =G6*Inputs!$F$14 | H8: =H6*Inputs!$F$14
B9: Operating income (EBIT) | D9: =D7-D8 | E9: =E7-E8 | F9: =F7-F8 | G9: =G7-G8 | H9: =H7-H8
B10: Tax on EBIT | D10: =D9*Inputs!$F$18 | E10: =E9*Inputs!$F$18 | F10: =F9*Inputs!$F$18 | G10: =G9*Inputs!$F$18 | H10: =H9*Inputs!$F$18
B11: NOPAT | D11: =D9*(1-Inputs!$F$18) | E11: =E9*(1-Inputs!$F$18) | F11: =F9*(1-Inputs!$F$18) | G11: =G9*(1-Inputs!$F$18) | H11: =H9*(1-Inputs!$F$18)
B12: D&A | D12: =D6*Inputs!$F$15 | E12: =E6*Inputs!$F$15 | F12: =F6*Inputs!$F$15 | G12: =G6*Inputs!$F$15 | H12: =H6*Inputs!$F$15
B13: Capex | D13: =D6*Inputs!$F$16 | E13: =E6*Inputs!$F$16 | F13: =F6*Inputs!$F$16 | G13: =G6*Inputs!$F$16 | H13: =H6*Inputs!$F$16
B14: Net working capital | C14: =Historicals!G34 | D14: =D6*Inputs!$F$17 | E14: =E6*Inputs!$F$17 | F14: =F6*Inputs!$F$17 | G14: =G6*Inputs!$F$17 | H14: =H6*Inputs!$F$17
B15: Change in NWC | D15: =D14-C14 | E15: =E14-D14 | F15: =F14-E14 | G15: =G14-F14 | H15: =H14-G14
B16: Unlevered free cash flow | D16: =D11+D12-D13-D15 | E16: =E11+E12-E13-E15 | F16: =F11+F12-F13-F15 | G16: =G11+G12-G13-G15 | H16: =H11+H12-H13-H15
B17: EBIT margin | D17: =D9/D6 | E17: =E9/E6 | F17: =F9/F6 | G17: =G9/G6 | H17: =H9/H6
B20: Chart data: revenue ($ billions) | C20: Actual | D20: Forecast
B21: FY2021 | C21: =Historicals!C4/1000
B22: FY2022 | C22: =Historicals!D4/1000
B23: FY2023 | C23: =Historicals!E4/1000
B24: FY2024 | C24: =Historicals!F4/1000
B25: FY2025 | C25: =Historicals!G4/1000
B26: FY2026 | D26: =D6/1000
B27: FY2027 | D27: =E6/1000
B28: FY2028 | D28: =F6/1000
B29: FY2029 | D29: =G6/1000
B30: FY2030 | D30: =H6/1000

Sheet DCF
B2: Discounted cash flow ($ millions) | H2: =Inputs!D4
C3: FY2026 | D3: FY2027 | E3: FY2028 | F3: FY2029 | G3: FY2030
B4: Unlevered free cash flow | C4: =Forecast!D16 | D4: =Forecast!E16 | E4: =Forecast!F16 | F4: =Forecast!G16 | G4: =Forecast!H16
B5: Discount factor (end of year) | C5: =1/(1+Inputs!$C$7)^Forecast!D4 | D5: =1/(1+Inputs!$C$7)^Forecast!E4 | E5: =1/(1+Inputs!$C$7)^Forecast!F4 | F5: =1/(1+Inputs!$C$7)^Forecast!G4 | G5: =1/(1+Inputs!$C$7)^Forecast!H4
B6: Present value | C6: =C4*C5 | D6: =D4*D5 | E6: =E4*E5 | F6: =F4*F5 | G6: =G4*G5
B8: Sum of present values | C8: =SUM(C6:G6)
B9: Terminal value at FY2030 | C9: =G4*(1+Inputs!C8)/(Inputs!C7-Inputs!C8)
B10: Present value of terminal value | C10: =C9*G5
B11: Enterprise value | C11: =C8+C10
B12: Debt (FY2025) | C12: =Historicals!G20+Historicals!G21
B13: Cash and short-term investments (FY2025) | C13: =Historicals!G18+Historicals!G19
B14: Net debt | C14: =C12-C13
B15: Equity value | C15: =C11-C14
B16: Diluted shares (millions, FY2025) | C16: =Historicals!G16
B17: Equity value per share ($) | C17: =C15/C16
B18: Terminal value share of enterprise value | C18: =C10/C11
B21: Sensitivity: equity value per share ($)
B22: WACC (down) x terminal growth (across)
C23: 0.02 | D23: 0.025 | E23: 0.03 | F23: 0.035 | G23: 0.04
B24: 0.07 | C24: =(Forecast!D16/(1+$B24)^1+Forecast!E16/(1+$B24)^2+Forecast!F16/(1+$B24)^3+Forecast!G16/(1+$B24)^4+Forecast!H16/(1+$B24)^5+Forecast!H16*(1+C$23)/($B24-C$23)/(1+$B24)^5-$C$14)/$C$16 | D24: =(Forecast!D16/(1+$B24)^1+Forecast!E16/(1+$B24)^2+Forecast!F16/(1+$B24)^3+Forecast!G16/(1+$B24)^4+Forecast!H16/(1+$B24)^5+Forecast!H16*(1+D$23)/($B24-D$23)/(1+$B24)^5-$C$14)/$C$16 | E24: =(Forecast!D16/(1+$B24)^1+Forecast!E16/(1+$B24)^2+Forecast!F16/(1+$B24)^3+Forecast!G16/(1+$B24)^4+Forecast!H16/(1+$B24)^5+Forecast!H16*(1+E$23)/($B24-E$23)/(1+$B24)^5-$C$14)/$C$16 | F24: =(Forecast!D16/(1+$B24)^1+Forecast!E16/(1+$B24)^2+Forecast!F16/(1+$B24)^3+Forecast!G16/(1+$B24)^4+Forecast!H16/(1+$B24)^5+Forecast!H16*(1+F$23)/($B24-F$23)/(1+$B24)^5-$C$14)/$C$16 | G24: =(Forecast!D16/(1+$B24)^1+Forecast!E16/(1+$B24)^2+Forecast!F16/(1+$B24)^3+Forecast!G16/(1+$B24)^4+Forecast!H16/(1+$B24)^5+Forecast!H16*(1+G$23)/($B24-G$23)/(1+$B24)^5-$C$14)/$C$16
B25: 0.075 | C25: =(Forecast!D16/(1+$B25)^1+Forecast!E16/(1+$B25)^2+Forecast!F16/(1+$B25)^3+Forecast!G16/(1+$B25)^4+Forecast!H16/(1+$B25)^5+Forecast!H16*(1+C$23)/($B25-C$23)/(1+$B25)^5-$C$14)/$C$16 | D25: =(Forecast!D16/(1+$B25)^1+Forecast!E16/(1+$B25)^2+Forecast!F16/(1+$B25)^3+Forecast!G16/(1+$B25)^4+Forecast!H16/(1+$B25)^5+Forecast!H16*(1+D$23)/($B25-D$23)/(1+$B25)^5-$C$14)/$C$16 | E25: =(Forecast!D16/(1+$B25)^1+Forecast!E16/(1+$B25)^2+Forecast!F16/(1+$B25)^3+Forecast!G16/(1+$B25)^4+Forecast!H16/(1+$B25)^5+Forecast!H16*(1+E$23)/($B25-E$23)/(1+$B25)^5-$C$14)/$C$16 | F25: =(Forecast!D16/(1+$B25)^1+Forecast!E16/(1+$B25)^2+Forecast!F16/(1+$B25)^3+Forecast!G16/(1+$B25)^4+Forecast!H16/(1+$B25)^5+Forecast!H16*(1+F$23)/($B25-F$23)/(1+$B25)^5-$C$14)/$C$16 | G25: =(Forecast!D16/(1+$B25)^1+Forecast!E16/(1+$B25)^2+Forecast!F16/(1+$B25)^3+Forecast!G16/(1+$B25)^4+Forecast!H16/(1+$B25)^5+Forecast!H16*(1+G$23)/($B25-G$23)/(1+$B25)^5-$C$14)/$C$16
B26: 0.08 | C26: =(Forecast!D16/(1+$B26)^1+Forecast!E16/(1+$B26)^2+Forecast!F16/(1+$B26)^3+Forecast!G16/(1+$B26)^4+Forecast!H16/(1+$B26)^5+Forecast!H16*(1+C$23)/($B26-C$23)/(1+$B26)^5-$C$14)/$C$16 | D26: =(Forecast!D16/(1+$B26)^1+Forecast!E16/(1+$B26)^2+Forecast!F16/(1+$B26)^3+Forecast!G16/(1+$B26)^4+Forecast!H16/(1+$B26)^5+Forecast!H16*(1+D$23)/($B26-D$23)/(1+$B26)^5-$C$14)/$C$16 | E26: =(Forecast!D16/(1+$B26)^1+Forecast!E16/(1+$B26)^2+Forecast!F16/(1+$B26)^3+Forecast!G16/(1+$B26)^4+Forecast!H16/(1+$B26)^5+Forecast!H16*(1+E$23)/($B26-E$23)/(1+$B26)^5-$C$14)/$C$16 | F26: =(Forecast!D16/(1+$B26)^1+Forecast!E16/(1+$B26)^2+Forecast!F16/(1+$B26)^3+Forecast!G16/(1+$B26)^4+Forecast!H16/(1+$B26)^5+Forecast!H16*(1+F$23)/($B26-F$23)/(1+$B26)^5-$C$14)/$C$16 | G26: =(Forecast!D16/(1+$B26)^1+Forecast!E16/(1+$B26)^2+Forecast!F16/(1+$B26)^3+Forecast!G16/(1+$B26)^4+Forecast!H16/(1+$B26)^5+Forecast!H16*(1+G$23)/($B26-G$23)/(1+$B26)^5-$C$14)/$C$16
B27: 0.085 | C27: =(Forecast!D16/(1+$B27)^1+Forecast!E16/(1+$B27)^2+Forecast!F16/(1+$B27)^3+Forecast!G16/(1+$B27)^4+Forecast!H16/(1+$B27)^5+Forecast!H16*(1+C$23)/($B27-C$23)/(1+$B27)^5-$C$14)/$C$16 | D27: =(Forecast!D16/(1+$B27)^1+Forecast!E16/(1+$B27)^2+Forecast!F16/(1+$B27)^3+Forecast!G16/(1+$B27)^4+Forecast!H16/(1+$B27)^5+Forecast!H16*(1+D$23)/($B27-D$23)/(1+$B27)^5-$C$14)/$C$16 | E27: =(Forecast!D16/(1+$B27)^1+Forecast!E16/(1+$B27)^2+Forecast!F16/(1+$B27)^3+Forecast!G16/(1+$B27)^4+Forecast!H16/(1+$B27)^5+Forecast!H16*(1+E$23)/($B27-E$23)/(1+$B27)^5-$C$14)/$C$16 | F27: =(Forecast!D16/(1+$B27)^1+Forecast!E16/(1+$B27)^2+Forecast!F16/(1+$B27)^3+Forecast!G16/(1+$B27)^4+Forecast!H16/(1+$B27)^5+Forecast!H16*(1+F$23)/($B27-F$23)/(1+$B27)^5-$C$14)/$C$16 | G27: =(Forecast!D16/(1+$B27)^1+Forecast!E16/(1+$B27)^2+Forecast!F16/(1+$B27)^3+Forecast!G16/(1+$B27)^4+Forecast!H16/(1+$B27)^5+Forecast!H16*(1+G$23)/($B27-G$23)/(1+$B27)^5-$C$14)/$C$16
B28: 0.09 | C28: =(Forecast!D16/(1+$B28)^1+Forecast!E16/(1+$B28)^2+Forecast!F16/(1+$B28)^3+Forecast!G16/(1+$B28)^4+Forecast!H16/(1+$B28)^5+Forecast!H16*(1+C$23)/($B28-C$23)/(1+$B28)^5-$C$14)/$C$16 | D28: =(Forecast!D16/(1+$B28)^1+Forecast!E16/(1+$B28)^2+Forecast!F16/(1+$B28)^3+Forecast!G16/(1+$B28)^4+Forecast!H16/(1+$B28)^5+Forecast!H16*(1+D$23)/($B28-D$23)/(1+$B28)^5-$C$14)/$C$16 | E28: =(Forecast!D16/(1+$B28)^1+Forecast!E16/(1+$B28)^2+Forecast!F16/(1+$B28)^3+Forecast!G16/(1+$B28)^4+Forecast!H16/(1+$B28)^5+Forecast!H16*(1+E$23)/($B28-E$23)/(1+$B28)^5-$C$14)/$C$16 | F28: =(Forecast!D16/(1+$B28)^1+Forecast!E16/(1+$B28)^2+Forecast!F16/(1+$B28)^3+Forecast!G16/(1+$B28)^4+Forecast!H16/(1+$B28)^5+Forecast!H16*(1+F$23)/($B28-F$23)/(1+$B28)^5-$C$14)/$C$16 | G28: =(Forecast!D16/(1+$B28)^1+Forecast!E16/(1+$B28)^2+Forecast!F16/(1+$B28)^3+Forecast!G16/(1+$B28)^4+Forecast!H16/(1+$B28)^5+Forecast!H16*(1+G$23)/($B28-G$23)/(1+$B28)^5-$C$14)/$C$16

Sheet Checks
B2: Model checks
B3: Overall | C3: =IF(AND(C5:C10),"ALL CHECKS PASS","CHECK FAILED")
B5: Operating income: calculated = reported, every year (to $1M) | C5: =MAX(ABS(Historicals!C8-Historicals!C9),ABS(Historicals!D8-Historicals!D9),ABS(Historicals!E8-Historicals!E9),ABS(Historicals!F8-Historicals!F9),ABS(Historicals!G8-Historicals!G9))<1
B6: Scenario is 1, 2 or 3 | C6: =AND(Inputs!C4>=1,Inputs!C4<=3,INT(Inputs!C4)=Inputs!C4)
B7: WACC is above terminal growth | C7: =Inputs!C7>Inputs!C8
B8: Sensitivity grid's 8% / 3% cell = DCF result (when those are the live inputs) | C8: =IF(AND(Inputs!C7=0.08,Inputs!C8=0.03),ABS(DCF!E26-DCF!C17)<0.005,TRUE)
B9: Forecast revenue grows from FY2025 actual | C9: =Forecast!D6>0
B10: Equity value per share is a number | C10: =ISNUMBER(DCF!C17)
